car_crash_detection/CrashUtils.py
car_crash_detection/__init__.py
Car_Crash_Detection-0.0.5.dist-info/LICENCE
Car_Crash_Detection-0.0.5.dist-info/METADATA
Car_Crash_Detection-0.0.5.dist-info/WHEEL
Car_Crash_Detection-0.0.5.dist-info/top_level.txt
Car_Crash_Detection-0.0.5.dist-info/RECORD
