Metadata-Version: 2.1
Name: Car-Crash-Detection
Version: 0.0.5
Summary: Car Crash Detection From Surveillance Cameras and Video Streams
Home-page: https://github.com/MohamedSebaie/Car_Crash_Detection_From_Surveillance_Cameras-PyTorch
Author: Mohamed Sebaie
Author-email: mohamedsebaie1@gmail.com
License: UNKNOWN
Platform: UNKNOWN
Classifier: Programming Language :: Python :: 3
Classifier: License :: OSI Approved :: MIT License
Classifier: Operating System :: OS Independent
Requires-Python: >=3.7
License-File: LICENCE
